MatplotlibHuituMijiChuyiFix1/README.md
MatplotlibHuituMijiChuyiFix1/__init__.py
MatplotlibHuituMijiChuyiFix1/__main__.py
MatplotlibHuituMijiChuyiFix1/file.epub
MatplotlibHuituMijiChuyiFix1/index.html
MatplotlibHuituMijiChuyiFix1/css/__init__.py
MatplotlibHuituMijiChuyiFix1/css/annotations.css
MatplotlibHuituMijiChuyiFix1/css/main.css
MatplotlibHuituMijiChuyiFix1/css/normalize.css
MatplotlibHuituMijiChuyiFix1/css/popup.css
MatplotlibHuituMijiChuyiFix1/font/__init__.py
MatplotlibHuituMijiChuyiFix1/font/fontello.eot
MatplotlibHuituMijiChuyiFix1/font/fontello.svg
MatplotlibHuituMijiChuyiFix1/font/fontello.ttf
MatplotlibHuituMijiChuyiFix1/font/fontello.woff
MatplotlibHuituMijiChuyiFix1/img/__init__.py
MatplotlibHuituMijiChuyiFix1/img/annotator-glyph-sprite.png
MatplotlibHuituMijiChuyiFix1/img/annotator-icon-sprite.png
MatplotlibHuituMijiChuyiFix1/img/apple-touch-icon.png
MatplotlibHuituMijiChuyiFix1/img/cancelfullscreen.png
MatplotlibHuituMijiChuyiFix1/img/close.png
MatplotlibHuituMijiChuyiFix1/img/fullscreen.png
MatplotlibHuituMijiChuyiFix1/img/loader.gif
MatplotlibHuituMijiChuyiFix1/img/menu-icon.png
MatplotlibHuituMijiChuyiFix1/img/save.png
MatplotlibHuituMijiChuyiFix1/img/saved.png
MatplotlibHuituMijiChuyiFix1/img/settings-s.png
MatplotlibHuituMijiChuyiFix1/img/settings.png
MatplotlibHuituMijiChuyiFix1/img/star.png
MatplotlibHuituMijiChuyiFix1/js/__init__.py
MatplotlibHuituMijiChuyiFix1/js/epub.js
MatplotlibHuituMijiChuyiFix1/js/epub.min.js
MatplotlibHuituMijiChuyiFix1/js/epub.min.map
MatplotlibHuituMijiChuyiFix1/js/hooks.min.js
MatplotlibHuituMijiChuyiFix1/js/hooks.min.map
MatplotlibHuituMijiChuyiFix1/js/reader.js
MatplotlibHuituMijiChuyiFix1/js/reader.js.map
MatplotlibHuituMijiChuyiFix1/js/reader.min.js
MatplotlibHuituMijiChuyiFix1/js/reader.min.map
MatplotlibHuituMijiChuyiFix1/js/hooks/__init__.py
MatplotlibHuituMijiChuyiFix1/js/hooks/extensions/__init__.py
MatplotlibHuituMijiChuyiFix1/js/hooks/extensions/highlight.js
matplotlib_huitu_miji_chuyi_fix1-2025.3.24.1.dist-info/METADATA
matplotlib_huitu_miji_chuyi_fix1-2025.3.24.1.dist-info/WHEEL
matplotlib_huitu_miji_chuyi_fix1-2025.3.24.1.dist-info/entry_points.txt
matplotlib_huitu_miji_chuyi_fix1-2025.3.24.1.dist-info/top_level.txt
matplotlib_huitu_miji_chuyi_fix1-2025.3.24.1.dist-info/RECORD
